LICENSE
MANIFEST.in
README.rst
setup.py
flask_phantom_emoji/__init__.py
flask_phantom_emoji.egg-info/PKG-INFO
flask_phantom_emoji.egg-info/SOURCES.txt
flask_phantom_emoji.egg-info/dependency_links.txt
flask_phantom_emoji.egg-info/not-zip-safe
flask_phantom_emoji.egg-info/requires.txt
flask_phantom_emoji.egg-info/top_level.txt
flask_phantom_emoji/PhantomOpenEmoji/emoji/Aquarius.svg
flask_phantom_emoji/PhantomOpenEmoji/emoji/Aries.svg
flask_phantom_emoji/PhantomOpenEmoji/emoji/Cancer.svg
flask_phantom_emoji/PhantomOpenEmoji/emoji/Capricorn.svg
flask_phantom_emoji/PhantomOpenEmoji/emoji/Charlie.svg
flask_phantom_emoji/PhantomOpenEmoji/emoji/Gemini.svg
flask_phantom_emoji/PhantomOpenEmoji/emoji/Happy_FMC.svg
flask_phantom_emoji/PhantomOpenEmoji/emoji/Leo.svg
flask_phantom_emoji/PhantomOpenEmoji/emoji/Libra.svg
flask_phantom_emoji/PhantomOpenEmoji/emoji/Pisces.svg
flask_phantom_emoji/PhantomOpenEmoji/emoji/Sagittarius.svg
flask_phantom_emoji/PhantomOpenEmoji/emoji/Scorpius.svg
flask_phantom_emoji/PhantomOpenEmoji/emoji/Taurus.svg
flask_phantom_emoji/PhantomOpenEmoji/emoji/Virgo.svg
flask_phantom_emoji/PhantomOpenEmoji/emoji/anchor.svg
flask_phantom_emoji/PhantomOpenEmoji/emoji/angry_face.svg
flask_phantom_emoji/PhantomOpenEmoji/emoji/anguished.svg
flask_phantom_emoji/PhantomOpenEmoji/emoji/apple_of_discord.svg
flask_phantom_emoji/PhantomOpenEmoji/emoji/astonished_face.svg
flask_phantom_emoji/PhantomOpenEmoji/emoji/bactrian_camel.svg
flask_phantom_emoji/PhantomOpenEmoji/emoji/beer_mug.svg
flask_phantom_emoji/PhantomOpenEmoji/emoji/bento_box.svg
flask_phantom_emoji/PhantomOpenEmoji/emoji/blowfish.svg
flask_phantom_emoji/PhantomOpenEmoji/emoji/blush.svg
flask_phantom_emoji/PhantomOpenEmoji/emoji/boar.svg
flask_phantom_emoji/PhantomOpenEmoji/emoji/bowtie.svg
flask_phantom_emoji/PhantomOpenEmoji/emoji/bus_stop.svg
flask_phantom_emoji/PhantomOpenEmoji/emoji/cactus.svg
flask_phantom_emoji/PhantomOpenEmoji/emoji/cat_face.svg
flask_phantom_emoji/PhantomOpenEmoji/emoji/cat_face_with_tears_of_joy.svg
flask_phantom_emoji/PhantomOpenEmoji/emoji/cat_face_with_wry_smile.svg
flask_phantom_emoji/PhantomOpenEmoji/emoji/chicken.svg
flask_phantom_emoji/PhantomOpenEmoji/emoji/circled_ideograph_secret.svg
