Metadata-Version: 1.0
Name: flask-phantom-emoji
Version: 0.1.4
Summary: Add phantom emoji's to your flask application
Home-page: https://github.com/nickw444/flask-phantom-emoji
Author: Nick Whyte
Author-email: nick@nickwhyte.com
License: UNKNOWN
Platform: UNKNOWN
